ripiu/cmsplugin_lasagna/__init__.py
ripiu/cmsplugin_lasagna/apps.py
ripiu/cmsplugin_lasagna/cms_plugins.py
ripiu/cmsplugin_lasagna/models.py
ripiu/cmsplugin_lasagna/locale/it/LC_MESSAGES/django.mo
ripiu/cmsplugin_lasagna/locale/it/LC_MESSAGES/django.po
ripiu/cmsplugin_lasagna/migrations/0001_initial.py
ripiu/cmsplugin_lasagna/migrations/0002_auto_20180102_1844.py
ripiu/cmsplugin_lasagna/migrations/0003_auto_20180108_0036.py
ripiu/cmsplugin_lasagna/migrations/__init__.py
ripiu/cmsplugin_lasagna/migrations/__pycache__/0001_initial.cpython-36.pyc
ripiu/cmsplugin_lasagna/migrations/__pycache__/0002_auto_20180102_1701.cpython-36.pyc
ripiu/cmsplugin_lasagna/migrations/__pycache__/0002_auto_20180102_1844.cpython-36.pyc
ripiu/cmsplugin_lasagna/migrations/__pycache__/0003_auto_20180108_0036.cpython-36.pyc
ripiu/cmsplugin_lasagna/migrations/__pycache__/__init__.cpython-36.pyc
ripiu/cmsplugin_lasagna/static/ripiu/cmsplugin_lasagna/css/lasagna.css
ripiu/cmsplugin_lasagna/templates/.DS_Store
ripiu/cmsplugin_lasagna/templates/ripiu/.DS_Store
ripiu/cmsplugin_lasagna/templates/ripiu/cmsplugin_lasagna/anchor.html
ripiu/cmsplugin_lasagna/templates/ripiu/cmsplugin_lasagna/color.html
ripiu/cmsplugin_lasagna/templates/ripiu/cmsplugin_lasagna/lasagna.html
ripiu/cmsplugin_lasagna/templates/ripiu/cmsplugin_lasagna/opacity.html
ripiu/cmsplugin_lasagna/templates/ripiu/cmsplugin_lasagna/valign.html
ripiu.cmsplugin_lasagna-0.1.4.dist-info/DESCRIPTION.rst
ripiu.cmsplugin_lasagna-0.1.4.dist-info/METADATA
ripiu.cmsplugin_lasagna-0.1.4.dist-info/RECORD
ripiu.cmsplugin_lasagna-0.1.4.dist-info/WHEEL
ripiu.cmsplugin_lasagna-0.1.4.dist-info/metadata.json
ripiu.cmsplugin_lasagna-0.1.4.dist-info/top_level.txt
